maintsim/Machine.py
maintsim/Scheduler.py
maintsim/System.py
maintsim/__init__.py
maintsim-0.1.2.dist-info/LICENSE.txt
maintsim-0.1.2.dist-info/METADATA
maintsim-0.1.2.dist-info/WHEEL
maintsim-0.1.2.dist-info/top_level.txt
maintsim-0.1.2.dist-info/RECORD
