Metadata-Version: 2.1
Name: maintsim
Version: 0.1.2
Summary: Simulation of maintenance for manufacturing
Home-page: https://github.com/m-hoff/maintsim
Author: Michael Hoffman
Author-email: MichaelHoffman@psu.edu
License: UNKNOWN
Platform: UNKNOWN
Classifier: Programming Language :: Python :: 3
Classifier: License :: OSI Approved :: MIT License
Classifier: Operating System :: OS Independent
